[
  {
    "id": 1,
    "name": "Cuerda",
    "description": "Juguete de cuerda.",
    "details": "",
    "image": "http://drive.google.com/uc?export=view&id=1tW97sURv66ONPl-VjNC9mzi_WtkPKenl"
  },
  {
    "id": 2,
    "name": "Hueso",
    "description": "Juguete de hueso.",
    "details": "",
    "image": "http://drive.google.com/uc?export=view&id=1CnriGMLv4Vgdpz-zpFYvSyl1r6QOgWC9"
  },
  {
    "id": 3,
    "name": "Juguete de lana",
    "description": "",
    "details": "",
    "image": "http://drive.google.com/uc?export=view&id=1B1YvQMQn9DwZebRAfUd9FBSMRoea6R1K"
  },
  {
    "id": 4,
    "name": "Pollo",
    "description": "Juguete de pollo.",
    "details": "",
    "image": "http://drive.google.com/uc?export=view&id=1WFX0CqUzjE2VOYqhIz_999AuE1OgTRTj"
  },
  {
    "id": 5,
    "name": "Ratón",
    "description": "Juguete de ratón.",
    "details": "",
    "image": "http://drive.google.com/uc?export=view&id=12BnuMo20jJNplgz7_V2BogOn7mvTemv7"
  },
  {
    "id": 6,
    "name": "Juguete para felino",
    "description": "",
    "details": "",
    "image": "http://drive.google.com/uc?export=view&id=1VNQWw-3cCJHGnF86DJlxa7URheW0qcfN"
  }
]
